README
setup.cfg
setup.py
EggsPacker.egg-info/PKG-INFO
EggsPacker.egg-info/SOURCES.txt
EggsPacker.egg-info/dependency_links.txt
EggsPacker.egg-info/entry_points.txt
EggsPacker.egg-info/top_level.txt
EggsPacker.egg-info/zip-safe
eggspacker/__init__.py
eggspacker/command.py
eggspacker/eggspacker.py