Metadata-Version: 1.0
Name: EggsPacker
Version: 0.1
Summary: A very simple egg fetcher
Home-page: UNKNOWN
Author: Christophe de Vienne
Author-email: cdevienne@gmail.com
License: Beer-ware
Platform: UNKNOWN
